tencentcloud/__init__.py
tencentcloud/iotvideo/__init__.py
tencentcloud/iotvideo/v20191126/__init__.py
tencentcloud/iotvideo/v20191126/errorcodes.py
tencentcloud/iotvideo/v20191126/iotvideo_client.py
tencentcloud/iotvideo/v20191126/models.py
tencentcloud/iotvideo/v20201215/__init__.py
tencentcloud/iotvideo/v20201215/errorcodes.py
tencentcloud/iotvideo/v20201215/iotvideo_client.py
tencentcloud/iotvideo/v20201215/models.py
tencentcloud/iotvideo/v20211125/__init__.py
tencentcloud/iotvideo/v20211125/errorcodes.py
tencentcloud/iotvideo/v20211125/iotvideo_client.py
tencentcloud/iotvideo/v20211125/models.py
tencentcloud_sdk_python_iotvideo-3.0.1459.dist-info/METADATA
tencentcloud_sdk_python_iotvideo-3.0.1459.dist-info/WHEEL
tencentcloud_sdk_python_iotvideo-3.0.1459.dist-info/top_level.txt
tencentcloud_sdk_python_iotvideo-3.0.1459.dist-info/RECORD
